odoo/addons/project_task_restrict_stage_timesheets/README.rst
odoo/addons/project_task_restrict_stage_timesheets/__init__.py
odoo/addons/project_task_restrict_stage_timesheets/__manifest__.py
odoo/addons/project_task_restrict_stage_timesheets/i18n/es.po
odoo/addons/project_task_restrict_stage_timesheets/models/__init__.py
odoo/addons/project_task_restrict_stage_timesheets/models/account_analytic_line.py
odoo/addons/project_task_restrict_stage_timesheets/models/project_task_type.py
odoo/addons/project_task_restrict_stage_timesheets/security/project_task_restrict_stage_timesheets_security.xml
odoo/addons/project_task_restrict_stage_timesheets/static/description/icon.png
odoo/addons/project_task_restrict_stage_timesheets/views/project_task_type_views.xml
odoo12_addon_project_task_restrict_stage_timesheets-12.0.1.0.0.dist-info/METADATA
odoo12_addon_project_task_restrict_stage_timesheets-12.0.1.0.0.dist-info/WHEEL
odoo12_addon_project_task_restrict_stage_timesheets-12.0.1.0.0.dist-info/top_level.txt
odoo12_addon_project_task_restrict_stage_timesheets-12.0.1.0.0.dist-info/RECORD
